{
    "coc.preferences.colorSupport": true,
    "coc.preferences.currentFunctionSymbolAutoUpdate": true,
    "coc.preferences.enableFloatHighlight": true,
    "coc.preferences.formatOnSaveFiletypes": ["*"],
    "coc.preferences.hoverTarget": "float",
    "coc.preferences.jumpCommand": "tab drop",
    "coc.preferences.useQuickfixForLocations": true,
    "codeLens.enable": true,
    "css.validate": false,
    "diagnostic.checkCurrentLine": true,
    "diagnostic.enableMessage": "always",
    "diagnostic.errorSign": "!!",
    "diagnostic.hintSign": "**",
    "diagnostic.messageTarget": "float",
    "diagnostic.virtualText": true,
    "diagnostic.warningSign": "!",
    "git.addGBlameToVirtualText": true,
    "git.enableGutters": true,
    "less.validate": false,
    "scss.validate": false,
    "signature.target": "float",
    "snippets.extends": {
        "javascriptreact": ["javascript"],
        "typescript": ["javascript"]
    },
    "stylelintplus.autoFixOnFormat": true,
    "stylelintplus.autoFixOnSave": true,
    "stylelintplus.validateOnSave": true,
    "stylelintplus.validateOnType": true,
    "suggest.floatEnable": true
}
